HypixelAPIWrapper/APIWrapper.py
HypixelAPIWrapper/__init__.py
HypixelAPIWrapper/exceptions.py
HypixelAPIWrapper/models.py
HypixelAPIWrapper/utils.py
HypixelAPIWrapper-0.1.2.dist-info/METADATA
HypixelAPIWrapper-0.1.2.dist-info/WHEEL
HypixelAPIWrapper-0.1.2.dist-info/top_level.txt
HypixelAPIWrapper-0.1.2.dist-info/RECORD
