Metadata-Version: 2.1
Name: HypixelAPIWrapper
Version: 0.1.2
Summary: Small library to work with Hypixel public API.
Home-page: https://HypixelAPIWrapper.readthedocs.io/
Author: Houwy
Author-email: nazandre1233@gmail.com
License: MIT
Platform: UNKNOWN
Classifier: Intended Audience :: Developers
Classifier: License :: OSI Approved :: MIT License
Classifier: Programming Language :: Python
Classifier: Programming Language :: Python :: 3
Classifier: Programming Language :: Python :: 3.6
Classifier: Programming Language :: Python :: 3.7
Classifier: Programming Language :: Python :: 3.8
Classifier: Programming Language :: Python :: 3.9
Classifier: Programming Language :: Python :: 3.10
Classifier: Operating System :: OS Independent
Requires-Dist: requests
Requires-Dist: python-nbt
